gitu/__init__.py
gitu/__main__.py
gitu/config_manager.py
gitu/functions.py
gitu/git_config.py
gitu-0.1.0.dist-info/LICENSE
gitu-0.1.0.dist-info/METADATA
gitu-0.1.0.dist-info/WHEEL
gitu-0.1.0.dist-info/entry_points.txt
gitu-0.1.0.dist-info/top_level.txt
gitu-0.1.0.dist-info/RECORD
