Metadata-Version: 2.1
Name: gitu
Version: 0.1.0
Summary: Account manager for git users with multiple accounts.
Home-page: https://github.com/HowyoungZhou/gitu
Author: Howyoung Zhou
Author-email: howyoungzhou@yahoo.com
License: UNKNOWN
Platform: UNKNOWN
Classifier: Programming Language :: Python :: 3
Classifier: License :: OSI Approved :: MIT License
Classifier: Operating System :: OS Independent
Requires-Python: >=3.5
